leetcode-python/__init__.py
leetcode-python/solutions.py
leetcode_python/__init__.py
leetcode_python/solutions.py
leetcode_solutions/__init__.py
leetcode_solutions/src/__init__.py
leetcode_solutions/src/outer_wilds.py
leetcode_solutions/test/__init__.py
leetcode_solutions/test/test_idgenerator.py
leetcode_python-0.0.1.dist-info/LICENSE
leetcode_python-0.0.1.dist-info/METADATA
leetcode_python-0.0.1.dist-info/WHEEL
leetcode_python-0.0.1.dist-info/top_level.txt
leetcode_python-0.0.1.dist-info/RECORD
